fieldtricks-0.1.2.dist-info/METADATA
fieldtricks-0.1.2.dist-info/WHEEL
fieldtricks/__init__.py
fieldtricks/razor/__init__.py
fieldtricks/razor/generic.py
fieldtricks/razor/schemas/QueryResult.json
fieldtricks/razor/simple.py
fieldtricks-0.1.2.dist-info/RECORD
