Metadata-Version: 2.1
Name: fieldtricks
Version: 0.1.2
Summary: Helper utilities for handling Pydantic models
Author-Email: Louis Maddox <louismmx@gmail.com>
License: MIT
Project-URL: Homepage, https://github.com/lmmx/fieldrouter
Project-URL: Repository, https://github.com/lmmx/fieldrouter.git
Requires-Python: >=3.10
Requires-Dist: fieldrouter
Requires-Dist: jsonschema
Requires-Dist: datamodel-code-generator
